amir/__init__.py
amir/utils.py
tests/__init__.py
tests/utils_test.py
amir-0.0.4.dist-info/LICENSE
amir-0.0.4.dist-info/METADATA
amir-0.0.4.dist-info/WHEEL
amir-0.0.4.dist-info/top_level.txt
amir-0.0.4.dist-info/RECORD
