Metadata-Version: 2.1
Name: amir
Version: 0.0.4
Summary: Utility Functions in Python
Home-page: http://www.amirhessam.com
Author: Amirhessam Tahmassebi
Author-email: amir.benny@gmail.com
License: MIT
Download-URL: https://github.com/amirhessam88/amirhessam/
Platform: UNKNOWN
Classifier: Programming Language :: Python :: 3
Classifier: License :: OSI Approved :: MIT License
Classifier: Operating System :: OS Independent
Classifier: Intended Audience :: Science/Research
Classifier: Natural Language :: English
Requires-Python: >=3.6
